[
  {
    "p": [
      14
    ],
    "s": "RATE"
  },
  {
    "p": [
      14
    ],
    "s": "REAL"
  },
  {
    "p": [
      3
    ],
    "s": "REASONS"
  },
  {
    "p": [
      3
    ],
    "s": "RECEIVE"
  },
  {
    "p": [
      3
    ],
    "s": "RECEIVING"
  },
  {
    "p": [
      14
    ],
    "s": "RECIPIENT"
  },
  {
    "p": [
      10
    ],
    "s": "RECIPIENTS"
  },
  {
    "p": [
      6
    ],
    "s": "RECOMMENDATIONS"
  },
  {
    "p": [
      13
    ],
    "s": "REDIRECT"
  },
  {
    "p": [
      16
    ],
    "s": "REDIRECTED"
  },
  {
    "p": [
      9
    ],
    "s": "REGARDLESS"
  },
  {
    "p": [
      14
    ],
    "s": "RELATIVELY"
  },
  {
    "p": [
      24,
      19
    ],
    "s": "RELEASE"
  },
  {
    "p": [
      14
    ],
    "s": "RELEVANCY"
  },
  {
    "p": [
      14
    ],
    "s": "RELEVANT"
  },
  {
    "p": [
      12
    ],
    "s": "REMOVE"
  },
  {
    "p": [
      11
    ],
    "s": "REPORT"
  },
  {
    "p": [
      5,
      3
    ],
    "s": "REPORTED"
  },
  {
    "p": [
      23,
      17,
      10,
      5,
      3
    ],
    "s": "REPORTS"
  },
  {
    "p": [
      14
    ],
    "s": "REQUEST"
  },
  {
    "p": [
      23,
      15
    ],
    "s": "REQUESTING"
  },
  {
    "p": [
      13
    ],
    "s": "REQUIRED"
  },
  {
    "p": [
      7,
      6
    ],
    "s": "REQUIREMENTS"
  },
  {
    "p": [
      14
    ],
    "s": "RESOURCES"
  },
  {
    "p": [
      14
    ],
    "s": "RESPECTIVE"
  },
  {
    "p": [
      14,
      11,
      3
    ],
    "s": "RESPONSE"
  },
  {
    "p": [
      14
    ],
    "s": "RESPONSES"
  },
  {
    "p": [
      14
    ],
    "s": "RESPONSIBILITY"
  },
  {
    "p": [
      12
    ],
    "s": "RETIRE"
  },
  {
    "p": [
      12
    ],
    "s": "RETIRED"
  },
  {
    "p": [
      12
    ],
    "s": "RETIRING"
  },
  {
    "p": [
      24
    ],
    "s": "REVISION"
  },
  {
    "p": [
      11
    ],
    "s": "RIGHT"
  },
  {
    "p": [
      11
    ],
    "s": "RIGHT-HAND"
  },
  {
    "p": [
      9
    ],
    "s": "RUNNING"
  }
]
